rhttp-0.1.2.dist-info/METADATA
rhttp-0.1.2.dist-info/WHEEL
rhttp/__init__.py
rhttp/rhttp.cpython-310-x86_64-linux-gnu.so
rhttp-0.1.2.dist-info/RECORD
